{
    "cordova-plugin-whitelist": {
        "source": {
            "type": "local",
            "path": "/Users/builder/BpcTooling/Cordova3/6.4.0/CorePlugins/cordova-plugin-whitelist"
        },
        "is_top_level": true,
        "variables": {
            "XWALK_VERSION": "22+",
            "XWALK_LITEVERSION": "xwalk_core_library_canary:17+",
            "XWALK_COMMANDLINE": "--disable-pull-to-refresh-effect",
            "XWALK_MODE": "embedded",
            "XWALK_MULTIPLEAPK": "true"
        }
    },
    "com.brodysoft.sqlitePlugin": {
        "source": {
            "type": "local",
            "path": "/Users/builder/.TelerikPluginsCache/com.phonegap.plugins.sqlite/1.1.0"
        },
        "is_top_level": true,
        "variables": {
            "XWALK_VERSION": "22+",
            "XWALK_LITEVERSION": "xwalk_core_library_canary:17+",
            "XWALK_COMMANDLINE": "--disable-pull-to-refresh-effect",
            "XWALK_MODE": "embedded",
            "XWALK_MULTIPLEAPK": "true"
        }
    },
    "cordova-plugin-battery-status": {
        "source": {
            "type": "local",
            "path": "/Users/builder/BpcTooling/Cordova3/6.4.0/CorePlugins/cordova-plugin-battery-status"
        },
        "is_top_level": true,
        "variables": {
            "XWALK_VERSION": "22+",
            "XWALK_LITEVERSION": "xwalk_core_library_canary:17+",
            "XWALK_COMMANDLINE": "--disable-pull-to-refresh-effect",
            "XWALK_MODE": "embedded",
            "XWALK_MULTIPLEAPK": "true"
        }
    },
    "cordova-plugin-console": {
        "source": {
            "type": "local",
            "path": "/Users/builder/BpcTooling/Cordova3/6.4.0/CorePlugins/cordova-plugin-console"
        },
        "is_top_level": true,
        "variables": {
            "XWALK_VERSION": "22+",
            "XWALK_LITEVERSION": "xwalk_core_library_canary:17+",
            "XWALK_COMMANDLINE": "--disable-pull-to-refresh-effect",
            "XWALK_MODE": "embedded",
            "XWALK_MULTIPLEAPK": "true"
        }
    },
    "cordova-plugin-crosswalk-webview": {
        "source": {
            "type": "local",
            "path": "/Users/builder/.TelerikPluginsCache/cordova-plugin-crosswalk-webview/2.2.0"
        },
        "is_top_level": true,
        "variables": {
            "XWALK_VERSION": "22+",
            "XWALK_LITEVERSION": "xwalk_core_library_canary:17+",
            "XWALK_COMMANDLINE": "--disable-pull-to-refresh-effect",
            "XWALK_MODE": "embedded",
            "XWALK_MULTIPLEAPK": "true"
        }
    },
    "cordova-plugin-device": {
        "source": {
            "type": "local",
            "path": "/Users/builder/BpcTooling/Cordova3/6.4.0/CorePlugins/cordova-plugin-device"
        },
        "is_top_level": true,
        "variables": {
            "XWALK_VERSION": "22+",
            "XWALK_LITEVERSION": "xwalk_core_library_canary:17+",
            "XWALK_COMMANDLINE": "--disable-pull-to-refresh-effect",
            "XWALK_MODE": "embedded",
            "XWALK_MULTIPLEAPK": "true"
        }
    },
    "cordova-plugin-device-motion": {
        "source": {
            "type": "local",
            "path": "/Users/builder/BpcTooling/Cordova3/6.4.0/CorePlugins/cordova-plugin-device-motion"
        },
        "is_top_level": true,
        "variables": {
            "XWALK_VERSION": "22+",
            "XWALK_LITEVERSION": "xwalk_core_library_canary:17+",
            "XWALK_COMMANDLINE": "--disable-pull-to-refresh-effect",
            "XWALK_MODE": "embedded",
            "XWALK_MULTIPLEAPK": "true"
        }
    },
    "cordova-plugin-device-orientation": {
        "source": {
            "type": "local",
            "path": "/Users/builder/BpcTooling/Cordova3/6.4.0/CorePlugins/cordova-plugin-device-orientation"
        },
        "is_top_level": true,
        "variables": {
            "XWALK_VERSION": "22+",
            "XWALK_LITEVERSION": "xwalk_core_library_canary:17+",
            "XWALK_COMMANDLINE": "--disable-pull-to-refresh-effect",
            "XWALK_MODE": "embedded",
            "XWALK_MULTIPLEAPK": "true"
        }
    },
    "cordova-plugin-dialogs": {
        "source": {
            "type": "local",
            "path": "/Users/builder/BpcTooling/Cordova3/6.4.0/CorePlugins/cordova-plugin-dialogs"
        },
        "is_top_level": true,
        "variables": {
            "XWALK_VERSION": "22+",
            "XWALK_LITEVERSION": "xwalk_core_library_canary:17+",
            "XWALK_COMMANDLINE": "--disable-pull-to-refresh-effect",
            "XWALK_MODE": "embedded",
            "XWALK_MULTIPLEAPK": "true"
        }
    },
    "cordova-plugin-file": {
        "source": {
            "type": "local",
            "path": "/Users/builder/BpcTooling/Cordova3/6.4.0/CorePlugins/cordova-plugin-file"
        },
        "is_top_level": true,
        "variables": {
            "XWALK_VERSION": "22+",
            "XWALK_LITEVERSION": "xwalk_core_library_canary:17+",
            "XWALK_COMMANDLINE": "--disable-pull-to-refresh-effect",
            "XWALK_MODE": "embedded",
            "XWALK_MULTIPLEAPK": "true"
        }
    },
    "cordova-plugin-compat": {
        "source": {
            "type": "registry",
            "id": "cordova-plugin-compat"
        },
        "is_top_level": false,
        "variables": {}
    },
    "cordova-plugin-file-transfer": {
        "source": {
            "type": "local",
            "path": "/Users/builder/BpcTooling/Cordova3/6.4.0/CorePlugins/cordova-plugin-file-transfer"
        },
        "is_top_level": true,
        "variables": {
            "XWALK_VERSION": "22+",
            "XWALK_LITEVERSION": "xwalk_core_library_canary:17+",
            "XWALK_COMMANDLINE": "--disable-pull-to-refresh-effect",
            "XWALK_MODE": "embedded",
            "XWALK_MULTIPLEAPK": "true"
        }
    },
    "cordova-plugin-inappbrowser": {
        "source": {
            "type": "local",
            "path": "/Users/builder/BpcTooling/Cordova3/6.4.0/CorePlugins/cordova-plugin-inappbrowser"
        },
        "is_top_level": true,
        "variables": {
            "XWALK_VERSION": "22+",
            "XWALK_LITEVERSION": "xwalk_core_library_canary:17+",
            "XWALK_COMMANDLINE": "--disable-pull-to-refresh-effect",
            "XWALK_MODE": "embedded",
            "XWALK_MULTIPLEAPK": "true"
        }
    },
    "cordova-plugin-network-information": {
        "source": {
            "type": "local",
            "path": "/Users/builder/BpcTooling/Cordova3/6.4.0/CorePlugins/cordova-plugin-network-information"
        },
        "is_top_level": true,
        "variables": {
            "XWALK_VERSION": "22+",
            "XWALK_LITEVERSION": "xwalk_core_library_canary:17+",
            "XWALK_COMMANDLINE": "--disable-pull-to-refresh-effect",
            "XWALK_MODE": "embedded",
            "XWALK_MULTIPLEAPK": "true"
        }
    },
    "cordova-plugin-splashscreen": {
        "source": {
            "type": "local",
            "path": "/Users/builder/BpcTooling/Cordova3/6.4.0/CorePlugins/cordova-plugin-splashscreen"
        },
        "is_top_level": true,
        "variables": {
            "XWALK_VERSION": "22+",
            "XWALK_LITEVERSION": "xwalk_core_library_canary:17+",
            "XWALK_COMMANDLINE": "--disable-pull-to-refresh-effect",
            "XWALK_MODE": "embedded",
            "XWALK_MULTIPLEAPK": "true"
        }
    },
    "cordova-plugin-statusbar": {
        "source": {
            "type": "local",
            "path": "/Users/builder/BpcTooling/Cordova3/6.4.0/CorePlugins/cordova-plugin-statusbar"
        },
        "is_top_level": true,
        "variables": {
            "XWALK_VERSION": "22+",
            "XWALK_LITEVERSION": "xwalk_core_library_canary:17+",
            "XWALK_COMMANDLINE": "--disable-pull-to-refresh-effect",
            "XWALK_MODE": "embedded",
            "XWALK_MULTIPLEAPK": "true"
        }
    },
    "cordova-plugin-vibration": {
        "source": {
            "type": "local",
            "path": "/Users/builder/BpcTooling/Cordova3/6.4.0/CorePlugins/cordova-plugin-vibration"
        },
        "is_top_level": true,
        "variables": {
            "XWALK_VERSION": "22+",
            "XWALK_LITEVERSION": "xwalk_core_library_canary:17+",
            "XWALK_COMMANDLINE": "--disable-pull-to-refresh-effect",
            "XWALK_MODE": "embedded",
            "XWALK_MULTIPLEAPK": "true"
        }
    },
    "nl.x-services.plugins.socialsharing": {
        "source": {
            "type": "local",
            "path": "/Users/builder/.TelerikPluginsCache/nl.x-services.plugins.socialsharing/5.1.1"
        },
        "is_top_level": true,
        "variables": {
            "XWALK_VERSION": "22+",
            "XWALK_LITEVERSION": "xwalk_core_library_canary:17+",
            "XWALK_COMMANDLINE": "--disable-pull-to-refresh-effect",
            "XWALK_MODE": "embedded",
            "XWALK_MULTIPLEAPK": "true"
        }
    },
    "com.telerik.cordovaPlatformSpecificFiles": {
        "source": {
            "type": "local",
            "path": "/tmp/builds/Rrbpzt2rMFPSivrsWo/app/Plugins/cordova-platform-specific-files"
        },
        "is_top_level": true,
        "variables": {
            "XWALK_VERSION": "22+",
            "XWALK_LITEVERSION": "xwalk_core_library_canary:17+",
            "XWALK_COMMANDLINE": "--disable-pull-to-refresh-effect",
            "XWALK_MODE": "embedded",
            "XWALK_MULTIPLEAPK": "true"
        }
    }
}